[
    {
        "hostname": "stage-scale10002.discord.gg",
        "ip": "35.215.115.126"
    },
    {
        "hostname": "stage-scale10004.discord.gg",
        "ip": "35.215.103.83"
    },
    {
        "hostname": "stage-scale10005.discord.gg",
        "ip": "35.215.76.142"
    },
    {
        "hostname": "stage-scale10011.discord.gg",
        "ip": "35.215.114.212"
    },
    {
        "hostname": "stage-scale10012.discord.gg",
        "ip": "35.215.74.81"
    },
    {
        "hostname": "stage-scale10013.discord.gg",
        "ip": "35.215.95.158"
    },
    {
        "hostname": "stage-scale10016.discord.gg",
        "ip": "35.215.116.60"
    }
]